progress_table/__init__.py
progress_table/common.py
progress_table/progress_table.py
progress_table/styles.py
progress_table-3.2.2.dist-info/METADATA
progress_table-3.2.2.dist-info/WHEEL
progress_table-3.2.2.dist-info/licenses/LICENSE.txt
progress_table-3.2.2.dist-info/RECORD
