Metadata-Version: 2.4
Name: progress-table
Version: 3.2.2
Summary: Display progress as a pretty table in the command line.
Project-URL: Home, https://github.com/gahaalt/progress-table
Project-URL: Documentation, https://github.com/sjmikler/progress-table/blob/main/docs
Author-email: Szymon Mikler <sjmikler@gmail.com>
License: MIT
License-File: LICENSE.txt
Classifier: License :: OSI Approved :: MIT License
Classifier: Programming Language :: Python :: 3
Classifier: Programming Language :: Python :: 3.7
Classifier: Programming Language :: Python :: 3.8
Classifier: Programming Language :: Python :: 3.9
Classifier: Programming Language :: Python :: 3.10
Classifier: Programming Language :: Python :: 3.11
Classifier: Programming Language :: Python :: 3.12
Classifier: Programming Language :: Python :: 3.13
Requires-Python: >=3.7
Requires-Dist: colorama
Requires-Dist: wcwidth
Provides-Extra: dev
Requires-Dist: hatch; extra == 'dev'
Requires-Dist: pyright; extra == 'dev'
Requires-Dist: pytest; extra == 'dev'
Requires-Dist: pytest-cov; extra == 'dev'
Requires-Dist: ruff; extra == 'dev'
Requires-Dist: twine; extra == 'dev'
